COPYING.txt
README.txt
opencore-configure.zcml
opencore-meta.zcml
setup.cfg
setup.py
Products/__init__.py
Products/OpenPlans/HISTORY.txt
Products/OpenPlans/Makefile
Products/OpenPlans/__init__.py
Products/OpenPlans/api.py
Products/OpenPlans/config.py
Products/OpenPlans/configure.zcml
Products/OpenPlans/meta.zcml
Products/OpenPlans/monkey.py
Products/OpenPlans/overrides.zcml
Products/OpenPlans/permissions.py
Products/OpenPlans/policy.py
Products/OpenPlans/refresh.txt
Products/OpenPlans/utils.py
Products/OpenPlans/version.txt
Products/OpenPlans/Extensions/Install.py
Products/OpenPlans/Extensions/__init__.py
Products/OpenPlans/Extensions/bootstrap_fletmenus.py
Products/OpenPlans/Extensions/checkhistory.py
Products/OpenPlans/Extensions/create_test_content.py
Products/OpenPlans/Extensions/find_duplicate_emails.py
Products/OpenPlans/Extensions/mark_member_homes.py
Products/OpenPlans/Extensions/migrate_atdoc_openpage.py
Products/OpenPlans/Extensions/migrate_listen.py
Products/OpenPlans/Extensions/migrate_listen_permissions.py
Products/OpenPlans/Extensions/migrate_membership_roles.py
Products/OpenPlans/Extensions/migrate_project_workflow.py
Products/OpenPlans/Extensions/migrate_teams.py
Products/OpenPlans/Extensions/migrate_teams_to_projects.py
Products/OpenPlans/Extensions/migrate_wickeddoc_openpage.py
Products/OpenPlans/Extensions/migratemembers.py
Products/OpenPlans/Extensions/setup.py
Products/OpenPlans/Extensions/show_project_membership.py
Products/OpenPlans/Extensions/utils.py
Products/OpenPlans/Extensions/workflow.py
Products/OpenPlans/conf/depends.conf
Products/OpenPlans/conf/depends.xml
Products/OpenPlans/conf/plugins.conf
Products/OpenPlans/conf/plugins.xml
Products/OpenPlans/content/__init__.py
Products/OpenPlans/content/project.py
Products/OpenPlans/content/team.py
Products/OpenPlans/copy/project_index.html
Products/OpenPlans/copy/site_index.html
Products/OpenPlans/docs/Makefile
Products/OpenPlans/interfaces/__init__.py
Products/OpenPlans/interfaces/adding.py
opencore.egg-info/PKG-INFO
opencore.egg-info/SOURCES.txt
opencore.egg-info/dependency_links.txt
opencore.egg-info/not-zip-safe
opencore.egg-info/requires.txt
opencore.egg-info/top_level.txt
