Metadata-Version: 1.0
Name: opencore
Version: 0.9a4
Summary: Software that drives http://openplans.org
Home-page: http://www.openplans.org/projects/opencore
Author: The Open Planning Project
Author-email: opencore-dev@lists.openplans.org
License: GPLv3
Keywords: openplans openplans.org topp
Platform: UNKNOWN
